arzprice/__init__.py
arzprice/irarz.py
arzprice/tasnim.py
arzprice/tools.py
arzprice-0.0.1.dist-info/LICENSE
arzprice-0.0.1.dist-info/METADATA
arzprice-0.0.1.dist-info/WHEEL
arzprice-0.0.1.dist-info/top_level.txt
arzprice-0.0.1.dist-info/RECORD
