Metadata-Version: 2.1
Name: arzprice
Version: 0.0.1
Summary: you can get everythings price in iran to rial.
Home-page: https://github.com/Erfan-Bafandeh/arzprice
Author: Erfan Bafandeh
Author-email: user.enbh@gmail.com
Keywords: arz,price,crypto,arzprice
Classifier: Programming Language :: Python :: 3.6
Classifier: Programming Language :: Python :: 3.7
Classifier: Programming Language :: Python :: 3.8
Classifier: Programming Language :: Python :: 3.9
Classifier: Programming Language :: Python :: 3.10
Classifier: Programming Language :: Python :: 3.11
Classifier: Programming Language :: Python :: 3.12
Classifier: License :: OSI Approved :: MIT License
Requires-Python: ~=3.6
License-File: LICENSE
Requires-Dist: requests
Requires-Dist: colorama
Requires-Dist: beautifulsoup4
